poridhiframe/__init__.py
poridhiframe/api.py
poridhiframe/middleware.py
poridhiframe/orm.py
poridhiframe/response.py
poridhiframe-0.0.3.dist-info/METADATA
poridhiframe-0.0.3.dist-info/WHEEL
poridhiframe-0.0.3.dist-info/top_level.txt
poridhiframe-0.0.3.dist-info/RECORD
