Metadata-Version: 2.4
Name: poridhiframe
Version: 0.0.3
Summary: PoridhiFrame Python Web Framework built for learning purposes.
Author: Ahnaf Tajwear Nabil
Author-email: ahnafnabil14@gmail.com
License: MIT
Classifier: Development Status :: 3 - Alpha
Classifier: Intended Audience :: Developers
Classifier: License :: OSI Approved :: MIT License
Classifier: Programming Language :: Python :: 3
Classifier: Programming Language :: Python :: 3.6
Classifier: Programming Language :: Python :: 3.7
Classifier: Programming Language :: Python :: 3.8
Classifier: Programming Language :: Python :: 3.9
Classifier: Topic :: Internet :: WWW/HTTP :: WSGI :: Application
Requires-Python: >=3.6.0
Requires-Dist: Jinja2==3.1.2
Requires-Dist: parse==1.19.0
Requires-Dist: requests==2.28.1
Requires-Dist: requests-wsgi-adapter==0.4.1
Requires-Dist: WebOb==1.8.7
Requires-Dist: whitenoise==6.2.0
Dynamic: author
Dynamic: author-email
Dynamic: classifier
Dynamic: description
Dynamic: description-content-type
Dynamic: license
Dynamic: requires-dist
Dynamic: requires-python
Dynamic: summary
